auralis/__init__.py
auralis/config.py
auralis/ecapa.py
auralis/file_utils.py
auralis/processing.py
auralis/scorer.py
auralis/validators.py
auralis/data/__init__.py
auralis/data/centroid_healthy.npy
auralis/data/fatigue_axis.npy
auralis/data/high_percentile.npz
auralis/data/low_percentile.npz
auralis/data/reference_embeddings_192-d.npy
auralis/models/__init__.py
auralis/models/config.yaml
auralis/models/ecapa_supcon_model.pth
auralis_vfs-1.1.0.dist-info/METADATA
auralis_vfs-1.1.0.dist-info/WHEEL
auralis_vfs-1.1.0.dist-info/top_level.txt
auralis_vfs-1.1.0.dist-info/RECORD
