Metadata-Version: 2.4
Name: auralis-vfs
Version: 1.1.0
Summary: Objective vocal fatigue scoring from speech using health-centric ECAPA-TDNN-VHE embeddings with standardized preprocessing and reproducible benchmarking.
Author: "Muhammad Khubaib Ahmad"
Author-email: Muhammad Khubaib Ahmad <muhammadkhubaibahmad854@gmail.com>
License: MIT
Project-URL: Homepage, https://github.com/Khubaib8281/auralis-vfs
Project-URL: Paper, https://doi.org/10.5281/zenodo.18305757
Requires-Python: >=3.9
Requires-Dist: numpy>=1.23
Requires-Dist: torch>=2.1.1
Requires-Dist: torchaudio>=2.1.1
Requires-Dist: soundfile
Requires-Dist: scipy
Requires-Dist: speechbrain>=1.0.3
Requires-Dist: pydub
Requires-Dist: ffmpeg
